melipayamak/__init__.py
melipayamak/branch.py
melipayamak/branchAsync.py
melipayamak/contacts.py
melipayamak/contactsAsync.py
melipayamak/melipayamak.py
melipayamak/ticket.py
melipayamak/ticketAsync.py
melipayamak/users.py
melipayamak/usersAsync.py
melipayamak/sms/__init__.py
melipayamak/sms/rest.py
melipayamak/sms/restAsync.py
melipayamak/sms/soap.py
melipayamak/sms/soapAsync.py
melipayamak-1.0.1.dist-info/METADATA
melipayamak-1.0.1.dist-info/WHEEL
melipayamak-1.0.1.dist-info/top_level.txt
melipayamak-1.0.1.dist-info/RECORD
