Metadata-Version: 2.1
Name: melipayamak
Version: 1.0.1
Summary: Melipayamak python SDK
Author-email: Melipayamak <info@melipayamak.com>
License: MIT
Project-URL: Homepage, https://github.com/Melipayamak/melipayamak-python
Project-URL: Issues, https://github.com/Melipayamak/melipayamak-python/issues
Classifier: Programming Language :: Python :: 3
Classifier: License :: OSI Approved :: MIT License
Classifier: Operating System :: OS Independent
Requires-Python: >=3.8
Requires-Dist: zeep>=4.3.1
Requires-Dist: requests>=2.32.3
Requires-Dist: aiohttp>=3.11.2
Requires-Dist: asyncio>=3.4.3
